stig_edit/__init__.py
stig_edit/ckl_editor.py
stig_edit/handler.py
stig_edit-1.0.6.dist-info/METADATA
stig_edit-1.0.6.dist-info/WHEEL
stig_edit-1.0.6.dist-info/licenses/LICENSE
stig_edit-1.0.6.dist-info/RECORD
