Metadata-Version: 2.1
Name: stig_edit
Version: 1.0.6
Summary: A small package that allows you to easily edit STIG (CKL files) quickly.
Project-URL: Homepage, https://github.com/FourHole/stig_edit
Project-URL: Bug Tracker, https://github.com/FourHole/stig_edit/issues
Author-email: fourhole <fourhole7@gmail.com>
License-File: LICENSE
Classifier: License :: OSI Approved :: MIT License
Classifier: Operating System :: OS Independent
Classifier: Programming Language :: Python :: 3
Requires-Python: >=3.7
